claude_statusline/__init__.py
claude_statusline/__main__.py
claude_statusline/cli/__init__.py
claude_statusline/cli/context_stats.py
claude_statusline/cli/statusline.py
claude_statusline/core/__init__.py
claude_statusline/core/colors.py
claude_statusline/core/config.py
claude_statusline/core/git.py
claude_statusline/core/state.py
claude_statusline/formatters/__init__.py
claude_statusline/formatters/time.py
claude_statusline/formatters/tokens.py
claude_statusline/graphs/__init__.py
claude_statusline/graphs/renderer.py
claude_statusline/graphs/statistics.py
cc_context_stats-1.3.1.dist-info/METADATA
cc_context_stats-1.3.1.dist-info/WHEEL
cc_context_stats-1.3.1.dist-info/entry_points.txt
cc_context_stats-1.3.1.dist-info/RECORD
